jsonpath_ext/__init__.py
jsonpath_ext/__main__.py
jsonpath_ext/cli.py
jsonpath_ext/environment.py
jsonpath_ext/exceptions.py
jsonpath_ext/filter_expressions.py
jsonpath_ext/lex.py
jsonpath_ext/node.py
jsonpath_ext/parse.py
jsonpath_ext/query.py
jsonpath_ext/segments.py
jsonpath_ext/selectors.py
jsonpath_ext/tokens.py
jsonpath_ext/function_extensions/__init__.py
jsonpath_ext/function_extensions/_pattern.py
jsonpath_ext/function_extensions/count.py
jsonpath_ext/function_extensions/filter_function.py
jsonpath_ext/function_extensions/length.py
jsonpath_ext/function_extensions/match.py
jsonpath_ext/function_extensions/search.py
jsonpath_ext/function_extensions/value.py
jsonpath_ext/utils/__init__.py
jsonpath_ext/utils/nondeterministic_descent.py
jsonpath_ext-0.0.5.dist-info/LICENSE.txt
jsonpath_ext-0.0.5.dist-info/METADATA
jsonpath_ext-0.0.5.dist-info/WHEEL
jsonpath_ext-0.0.5.dist-info/entry_points.txt
jsonpath_ext-0.0.5.dist-info/top_level.txt
jsonpath_ext-0.0.5.dist-info/RECORD
