Metadata-Version: 2.1
Name: jsonpath-ext
Version: 0.0.5
Summary: RFC 9535 - JSONPath: Query Expressions for JSON in Python with non-rfc9535 extensions.
Author-email: Riccardo Tiebax <riccardo.t@gmail.com>
Project-URL: Documentation, https://jg-rp.github.io/python-jsonpath-ext/
Project-URL: Issues, https://github.com/riccardo92/python-jsonpath-ext/issues
Project-URL: Source, https://github.com/riccardo92/python-jsonpath-ext
Classifier: Development Status :: 4 - Beta
Classifier: Intended Audience :: Developers
Classifier: License :: OSI Approved :: MIT License
Classifier: Programming Language :: Python
Classifier: Programming Language :: Python :: 3.8
Classifier: Programming Language :: Python :: 3.9
Classifier: Programming Language :: Python :: 3.10
Classifier: Programming Language :: Python :: 3.11
Classifier: Programming Language :: Python :: 3.12
Classifier: Programming Language :: Python :: Implementation :: CPython
Classifier: Programming Language :: Python :: Implementation :: PyPy
Requires-Python: >=3.8
License-File: LICENSE.txt
Requires-Dist: regex
Requires-Dist: iregexp-check >=0.1.3
Provides-Extra: pre-commit
Requires-Dist: deptry ==0.16.1 ; extra == 'pre-commit'
Requires-Dist: pre-commit ==3.7.0 ; extra == 'pre-commit'
Requires-Dist: ruff ==0.4.2 ; extra == 'pre-commit'
Requires-Dist: tox ==4.15.1 ; extra == 'pre-commit'
